MANIFEST.in
README.rst
setup.py
docs/build/Makefile
docs/build/make.bat
docs/source/changelog.rst
docs/source/conf.py
docs/source/index.rst
docs/source/licence.rst
docs/source/overview.rst
docs/source/todo.rst
docs/source/.static/.hidden
src/sact/__init__.py
src/sact.recipe.postgresql.egg-info/PKG-INFO
src/sact.recipe.postgresql.egg-info/SOURCES.txt
src/sact.recipe.postgresql.egg-info/dependency_links.txt
src/sact.recipe.postgresql.egg-info/entry_points.txt
src/sact.recipe.postgresql.egg-info/namespace_packages.txt
src/sact.recipe.postgresql.egg-info/not-zip-safe
src/sact.recipe.postgresql.egg-info/requires.txt
src/sact.recipe.postgresql.egg-info/top_level.txt
src/sact/recipe/__init__.py
src/sact/recipe/postgresql/__init__.py
src/sact/recipe/postgresql/templates/environment.tmpl
src/sact/recipe/postgresql/templates/pg_hba.conf.tmpl
src/sact/recipe/postgresql/templates/pg_ident.conf.tmpl
src/sact/recipe/postgresql/templates/start.conf.tmpl