Metadata-Version: 1.1
Name: sact.recipe.postgresql
Version: 0.10.0
Summary: zc.buildout recipe to build PostgreSQL.
Home-page: http://github.com/securactive/sact.recipe.postgresql
Author: SecurActive SA
Author-email: opensource@securactive.net
License: BSD License
Keywords: buildout postgresql
Platform: UNKNOWN
Classifier: Development Status :: 4 - Beta
Classifier: Framework :: Buildout :: Recipe
Classifier: Intended Audience :: Developers
Classifier: Topic :: Software Development :: Build Tools
Classifier: Topic :: Software Development :: Libraries :: Python Modules
Classifier: License :: OSI Approved :: BSD License
Classifier: Operating System :: OS Independent
